openstack_mcp_server/__init__.py
openstack_mcp_server/__main__.py
openstack_mcp_server/_version.py
openstack_mcp_server/config.py
openstack_mcp_server/server.py
openstack_mcp_server/prompts/__init__.py
openstack_mcp_server/resources/__init__.py
openstack_mcp_server/tools/__init__.py
openstack_mcp_server/tools/base.py
openstack_mcp_server/tools/block_storage_tools.py
openstack_mcp_server/tools/compute_tools.py
openstack_mcp_server/tools/connection.py
openstack_mcp_server/tools/identity_tools.py
openstack_mcp_server/tools/image_tools.py
openstack_mcp_server/tools/network_tools.py
openstack_mcp_server/tools/request/__init__.py
openstack_mcp_server/tools/request/image.py
openstack_mcp_server/tools/request/network.py
openstack_mcp_server/tools/response/__init__.py
openstack_mcp_server/tools/response/block_storage.py
openstack_mcp_server/tools/response/compute.py
openstack_mcp_server/tools/response/identity.py
openstack_mcp_server/tools/response/image.py
openstack_mcp_server/tools/response/network.py
python_openstackmcp_server-1.0.0.dist-info/licenses/LICENSE
python_openstackmcp_server-1.0.0.dist-info/METADATA
python_openstackmcp_server-1.0.0.dist-info/WHEEL
python_openstackmcp_server-1.0.0.dist-info/entry_points.txt
python_openstackmcp_server-1.0.0.dist-info/top_level.txt
python_openstackmcp_server-1.0.0.dist-info/RECORD
