Metadata-Version: 2.4
Name: python-openstackmcp-server
Version: 1.0.0
Summary: A MCP server providing OpenStack services for MCP clients
Requires-Python: >=3.10
License-File: LICENSE
Requires-Dist: fastmcp>=2.11.3
Requires-Dist: openstacksdk>=4.6.0
Requires-Dist: pydantic>=2.11.7
Dynamic: license-file
